{
	"about": "https://jvndb.jvn.jp/ja/contents/2015/JVNDB-2015-002408.html",
	"title": "Net Nanny が共有の秘密鍵とルート CA 証明書を使用している問題",
	"link": "https://jvndb.jvn.jp/ja/contents/2015/JVNDB-2015-002408.html",
	"description": "Net Nanny は共有の秘密鍵とルート CA 証明書を使用するため、システムに対する HTTPS スプーフィングが可能になる問題が存在します。\r\n\r\nNet Nanny は、ルート CA 証明書とプロキシをインストールします。この証明書の生成に用いられる秘密鍵は、直接平文で取得できる形でプログラムに含まれています。攻撃者は、この秘密鍵を用いることで Net Nanny によって信頼される証明書を生成することが可能です。",
	"identifier": "JVNDB-2015-002408",
	"references": [
		{
			"text": "http://jvn.jp/vu/JVNVU90912447/",
			"source": "JVN",
			"id": "JVNVU#90912447"
		},
		{
			"text": "http://www.kb.cert.org/vuls/id/260780",
			"source": "CERT-VN",
			"id": "VU#260780"
		}
	],
	"cpe": [
		{
			"text": "cpe:/a:misc:contentwatch_net_nanny",
			"version": "2.2",
			"vendor": "ContentWatch, Inc.",
			"product": "Net Nanny"
		}
	],
	"cvss": [
		{
			"version": "2.0",
			"score": "6.8",
			"type": "Base",
			"severity": "Medium",
			"vector": "AV:N/AC:L/Au:S/C:C/I:N/A:N"
		}
	],
	"date": "2015-04-22T10:30+09:00",
	"issued": "2015-04-22T10:30+09:00",
	"modified": "2015-04-22T10:30+09:00"
}
